{
  "url": "https://emcasa.com/imoveis/sp/sao-paulo?nextView=true",
  "requestedUrl": "https://www.emcasa.com/imoveis/sp/sao-paulo?nextView=true",
  "timestamp": 1680952093662,
  "ranks": {
    "hundos": 4,
    "performance": 4,
    "accessibility": 6,
    "cumulative": 4
  },
  "lighthouse": {
    "version": "9.4.0",
    "performance": 0.68,
    "accessibility": 1,
    "bestPractices": 1,
    "seo": 1,
    "total": 368
  },
  "firstContentfulPaint": 2054.6769999999997,
  "firstMeaningfulPaint": 2054.6769999999997,
  "speedIndex": 3997.101966854163,
  "largestContentfulPaint": 2758.1629999999996,
  "totalBlockingTime": 754.5,
  "cumulativeLayoutShift": 0.021592827690972222,
  "timeToInteractive": 8025.677,
  "maxPotentialFirstInputDelay": 646,
  "timeToFirstByte": 43.71,
  "weight": {
    "summary": "82 requests • 918 KiB",
    "total": 939855,
    "image": 380389,
    "imageCount": 24,
    "script": 411727,
    "scriptCount": 25,
    "document": 46186,
    "font": 34379,
    "fontCount": 1,
    "stylesheet": 11868,
    "stylesheetCount": 5,
    "thirdParty": 477725,
    "thirdPartyCount": 32
  },
  "run": {
    "number": 2,
    "total": 3
  },
  "axe": {
    "passes": 2563,
    "violations": 11
  }
}