{
  "url": "https://www.emcasa.com/",
  "requestedUrl": "https://www.emcasa.com/",
  "timestamp": 1672139278374,
  "ranks": {
    "hundos": 4,
    "performance": 5,
    "accessibility": 5,
    "cumulative": 4
  },
  "lighthouse": {
    "version": "9.4.0",
    "performance": 0.33,
    "accessibility": 0.98,
    "bestPractices": 0.83,
    "seo": 1,
    "total": 314
  },
  "firstContentfulPaint": 5554.327,
  "firstMeaningfulPaint": 5554.327,
  "speedIndex": 5554.327,
  "largestContentfulPaint": 6760.409,
  "totalBlockingTime": 1274.1115,
  "cumulativeLayoutShift": 0.003924899631076388,
  "timeToInteractive": 7022.8775000000005,
  "maxPotentialFirstInputDelay": 966,
  "timeToFirstByte": 51.459,
  "weight": {
    "summary": "38 requests • 925 KiB",
    "total": 946777,
    "image": 127253,
    "imageCount": 17,
    "script": 535180,
    "scriptCount": 8,
    "document": 149341,
    "font": 34492,
    "fontCount": 1,
    "stylesheet": 14353,
    "stylesheetCount": 3,
    "thirdParty": 55412,
    "thirdPartyCount": 7
  },
  "run": {
    "number": 2,
    "total": 3
  },
  "axe": {
    "passes": 1207,
    "violations": 5
  }
}