{
  "url": "https://emcasa.com/imoveis/sp/sao-paulo/perdizes/rua-diana/id-1451?nextView=true",
  "requestedUrl": "https://www.emcasa.com/imoveis/sp/sao-paulo/perdizes/rua-diana/id-1451?nextView=true",
  "timestamp": 1687432241913,
  "ranks": {
    "hundos": 3,
    "performance": 7,
    "accessibility": 1,
    "cumulative": 3
  },
  "lighthouse": {
    "version": "9.4.0",
    "performance": 0.52,
    "accessibility": 1,
    "bestPractices": 1,
    "seo": 1,
    "total": 352
  },
  "firstContentfulPaint": 1837.489,
  "firstMeaningfulPaint": 1837.489,
  "speedIndex": 2661.815500543435,
  "largestContentfulPaint": 6007.489,
  "totalBlockingTime": 838.5,
  "cumulativeLayoutShift": 0.00003888575236002604,
  "timeToInteractive": 6907.489,
  "maxPotentialFirstInputDelay": 387,
  "timeToFirstByte": 38.956,
  "weight": {
    "summary": "53 requests • 710 KiB",
    "total": 727490,
    "image": 230456,
    "imageCount": 6,
    "script": 367680,
    "scriptCount": 23,
    "document": 26880,
    "font": 34378,
    "fontCount": 1,
    "stylesheet": 14197,
    "stylesheetCount": 3,
    "thirdParty": 250545,
    "thirdPartyCount": 10
  },
  "run": {
    "number": 3,
    "total": 3
  },
  "axe": {
    "passes": 1382,
    "violations": 1
  }
}