{
  "url": "https://www.emcasa.com/corretor-parceiro",
  "requestedUrl": "https://www.emcasa.com/corretor-parceiro",
  "timestamp": 1670065623777,
  "ranks": {
    "hundos": 3,
    "performance": 2,
    "accessibility": 4,
    "cumulative": 3
  },
  "lighthouse": {
    "version": "9.4.0",
    "performance": 0.43,
    "accessibility": 0.97,
    "bestPractices": 0.83,
    "seo": 0.92,
    "total": 318
  },
  "firstContentfulPaint": 5384.81,
  "firstMeaningfulPaint": 5384.81,
  "speedIndex": 5384.81,
  "largestContentfulPaint": 5384.81,
  "totalBlockingTime": 774.8030000000003,
  "cumulativeLayoutShift": 0.008091176138983833,
  "timeToInteractive": 6773.6590000000015,
  "maxPotentialFirstInputDelay": 845,
  "timeToFirstByte": 740.813,
  "weight": {
    "summary": "39 requests • 819 KiB",
    "total": 838281,
    "image": 19361,
    "imageCount": 18,
    "script": 535072,
    "scriptCount": 8,
    "document": 149730,
    "font": 34020,
    "fontCount": 1,
    "stylesheet": 14362,
    "stylesheetCount": 3,
    "thirdParty": 54924,
    "thirdPartyCount": 7
  },
  "run": {
    "number": 1,
    "total": 3
  },
  "axe": {
    "passes": 789,
    "violations": 4
  }
}