{
  "url": "https://www.emcasa.com/corretor-parceiro",
  "requestedUrl": "https://www.emcasa.com/corretor-parceiro",
  "timestamp": 1649329654336,
  "ranks": {
    "hundos": 2,
    "performance": 2,
    "accessibility": 5,
    "cumulative": 2
  },
  "lighthouse": {
    "version": "9.4.0",
    "performance": 0.4,
    "accessibility": 0.97,
    "bestPractices": 0.83,
    "seo": 1,
    "total": 323
  },
  "firstContentfulPaint": 2862.698,
  "firstMeaningfulPaint": 2862.698,
  "speedIndex": 4663.5910207189245,
  "largestContentfulPaint": 7040.049999999999,
  "totalBlockingTime": 1154,
  "cumulativeLayoutShift": 0.008055252922905817,
  "timeToInteractive": 7805.697999999999,
  "maxPotentialFirstInputDelay": 1027,
  "timeToFirstByte": 53.762,
  "weight": {
    "summary": "39 requests • 807 KiB",
    "total": 826393,
    "image": 18621,
    "imageCount": 17,
    "script": 528980,
    "scriptCount": 10,
    "document": 147046,
    "font": 34152,
    "fontCount": 1,
    "stylesheet": 13566,
    "stylesheetCount": 3,
    "thirdParty": 53974,
    "thirdPartyCount": 8
  },
  "run": {
    "number": 1,
    "total": 3
  },
  "axe": {
    "passes": 791,
    "violations": 4
  }
}