{
  "url": "https://www.emcasa.com/imoveis/sp/sao-paulo",
  "requestedUrl": "https://www.emcasa.com/imoveis/sp/sao-paulo",
  "timestamp": 1653477018184,
  "ranks": {
    "hundos": 5,
    "performance": 4,
    "accessibility": 1,
    "cumulative": 4
  },
  "lighthouse": {
    "version": "9.4.0",
    "performance": 0.26,
    "accessibility": 1,
    "bestPractices": 0.75,
    "seo": 1,
    "total": 301
  },
  "firstContentfulPaint": 6044.924000000001,
  "firstMeaningfulPaint": 6044.924000000001,
  "speedIndex": 6666.945029469132,
  "largestContentfulPaint": 7239.0064999999995,
  "totalBlockingTime": 1661.5,
  "cumulativeLayoutShift": 0.00007421875,
  "timeToInteractive": 10405.4095,
  "maxPotentialFirstInputDelay": 1248,
  "timeToFirstByte": 48.82200000000001,
  "weight": {
    "summary": "51 requests • 1,307 KiB",
    "total": 1338590,
    "image": 268725,
    "imageCount": 27,
    "script": 729940,
    "scriptCount": 13,
    "document": 206609,
    "font": 34153,
    "fontCount": 1,
    "stylesheet": 12197,
    "stylesheetCount": 2,
    "thirdParty": 512277,
    "thirdPartyCount": 26
  },
  "run": {
    "number": 3,
    "total": 3
  },
  "axe": {
    "passes": 1283,
    "violations": 2
  }
}