{
  "url": "https://www.emcasa.com/imoveis/sp/sao-paulo/perdizes/rua-diana/id-1451",
  "requestedUrl": "https://www.emcasa.com/imoveis/sp/sao-paulo/perdizes/rua-diana/id-1451",
  "timestamp": 1666696244575,
  "ranks": {
    "hundos": 6,
    "performance": 5,
    "accessibility": 6,
    "cumulative": 6
  },
  "lighthouse": {
    "version": "9.4.0",
    "performance": 0.31,
    "accessibility": 0.9,
    "bestPractices": 0.83,
    "seo": 0.91,
    "total": 295
  },
  "firstContentfulPaint": 5696.3060000000005,
  "firstMeaningfulPaint": 6033.3060000000005,
  "speedIndex": 5706.472739873782,
  "largestContentfulPaint": 7443.940500000001,
  "totalBlockingTime": 1287.0429999999988,
  "cumulativeLayoutShift": 0.001183344523111979,
  "timeToInteractive": 8029.875999999999,
  "maxPotentialFirstInputDelay": 673.9999999999991,
  "timeToFirstByte": 53.239000000000004,
  "weight": {
    "summary": "69 requests • 1,198 KiB",
    "total": 1227193,
    "image": 120292,
    "imageCount": 30,
    "script": 768344,
    "scriptCount": 24,
    "document": 199609,
    "font": 34020,
    "fontCount": 1,
    "stylesheet": 16390,
    "stylesheetCount": 4,
    "thirdParty": 346620,
    "thirdPartyCount": 31
  },
  "run": {
    "number": 3,
    "total": 3
  },
  "axe": {
    "passes": 1590,
    "violations": 5
  }
}